LICENSE
README.md
setup.py
wayback_news_search.egg-info/PKG-INFO
wayback_news_search.egg-info/SOURCES.txt
wayback_news_search.egg-info/dependency_links.txt
wayback_news_search.egg-info/requires.txt
wayback_news_search.egg-info/top_level.txt
waybacknews/__init__.py
waybacknews/searchapi.py
waybacknews/util.py