Metadata-Version: 2.1
Name: wayback-news-search
Version: 1.0.3
Summary: Wayback Machine news archive search api client
Home-page: https://web.archive.org
Maintainer: Rahul Bhargava
Maintainer-email: r.bhargava@northeastern.edu
Project-URL: Bug Reports, https://github.com/mediacloud/wayback-news-search/issues
Project-URL: Source, https://github.com/mediacloud/wayback-news-search
Requires-Python: >3.7
Provides-Extra: dev
License-File: LICENSE
